{
  "meta": {
    "source": "replay",
    "replay_date": "2025-04-15",
    "balance": 153551.0,
    "risk_pct": 0.01,
    "replay_mode": true
  },
  "summary": {
    "total_trades": 1,
    "wins": 0,
    "losses": 1,
    "eod_exits": 0,
    "net_pnl": -3558.0,
    "start_balance": 153551.0,
    "end_balance": 149993.0,
    "kill_switch_hit": false
  },
  "trades": [
    {
      "trade_id": 1,
      "date": "2025-04-15",
      "fvg_type": "",
      "time_period": "",
      "risk_range": "",
      "setup": "mid_extreme",
      "side": "BUY",
      "entry_price": 18962.5,
      "stop_price": 18919.0,
      "target_price": 19006.0,
      "risk_pts": 43.5,
      "n_value": 1.0,
      "contracts": 4,
      "entry_time": "2025-04-15 13:45:14.829416437-04:00",
      "exit_time": "2025-04-15 13:53:53.184692943-04:00",
      "exit_price": 18918.25,
      "exit_reason": "SL",
      "pnl_pts": -44.25,
      "pnl_dollars": -3558.0,
      "is_win": false,
      "group_id": "962db5621477",
      "fvg_id": "ffecfdaf5a50"
    }
  ]
}