{
  "meta": {
    "source": "replay",
    "replay_date": "2024-07-09",
    "balance": 126657.0,
    "risk_pct": 0.01,
    "replay_mode": true
  },
  "summary": {
    "total_trades": 5,
    "wins": 2,
    "losses": 3,
    "eod_exits": 0,
    "net_pnl": 546.0,
    "start_balance": 126657.0,
    "end_balance": 127203.0,
    "kill_switch_hit": false
  },
  "trades": [
    {
      "trade_id": 1,
      "date": "2024-07-09",
      "fvg_type": "",
      "time_period": "",
      "risk_range": "",
      "setup": "mit_extreme",
      "side": "SELL",
      "entry_price": 20711.0,
      "stop_price": 20721.25,
      "target_price": 20680.25,
      "risk_pts": 10.25,
      "n_value": 3.0,
      "contracts": 3,
      "entry_time": "2024-07-09 10:35:25.620207101-04:00",
      "exit_time": "2024-07-09 10:37:11.203573799-04:00",
      "exit_price": 20721.25,
      "exit_reason": "SL",
      "pnl_pts": -10.25,
      "pnl_dollars": -628.5,
      "is_win": false,
      "group_id": "eabdc4c54198",
      "fvg_id": "8d2b3481856c"
    },
    {
      "trade_id": 2,
      "date": "2024-07-09",
      "fvg_type": "",
      "time_period": "",
      "risk_range": "",
      "setup": "mit_extreme",
      "side": "BUY",
      "entry_price": 20713.5,
      "stop_price": 20702.75,
      "target_price": 20745.75,
      "risk_pts": 10.75,
      "n_value": 3.0,
      "contracts": 2,
      "entry_time": "2024-07-09 10:49:52.685256569-04:00",
      "exit_time": "2024-07-09 10:56:30.729117711-04:00",
      "exit_price": 20702.5,
      "exit_reason": "SL",
      "pnl_pts": -11.0,
      "pnl_dollars": -449.0,
      "is_win": false,
      "group_id": "4d51835a5bc1",
      "fvg_id": "f00d078d77b9"
    },
    {
      "trade_id": 3,
      "date": "2024-07-09",
      "fvg_type": "",
      "time_period": "",
      "risk_range": "",
      "setup": "mit_extreme",
      "side": "SELL",
      "entry_price": 20680.75,
      "stop_price": 20695.5,
      "target_price": 20651.25,
      "risk_pts": 14.75,
      "n_value": 2.0,
      "contracts": 2,
      "entry_time": "2024-07-09 13:02:35.307480251-04:00",
      "exit_time": "2024-07-09 13:17:21.045307383-04:00",
      "exit_price": 20651.25,
      "exit_reason": "TP",
      "pnl_pts": 29.5,
      "pnl_dollars": 1171.0,
      "is_win": true,
      "group_id": "71e01ee58b2a",
      "fvg_id": "5e5819550588"
    },
    {
      "trade_id": 4,
      "date": "2024-07-09",
      "fvg_type": "",
      "time_period": "",
      "risk_range": "",
      "setup": "mit_extreme",
      "side": "BUY",
      "entry_price": 20646.25,
      "stop_price": 20629.5,
      "target_price": 20663.0,
      "risk_pts": 16.75,
      "n_value": 1.0,
      "contracts": 3,
      "entry_time": "2024-07-09 13:41:06.664149965-04:00",
      "exit_time": "2024-07-09 13:56:40.339174573-04:00",
      "exit_price": 20663.0,
      "exit_reason": "TP",
      "pnl_pts": 16.75,
      "pnl_dollars": 991.5,
      "is_win": true,
      "group_id": "533576ff44a9",
      "fvg_id": "9c5e3bca2c53"
    },
    {
      "trade_id": 5,
      "date": "2024-07-09",
      "fvg_type": "",
      "time_period": "",
      "risk_range": "",
      "setup": "mit_extreme",
      "side": "BUY",
      "entry_price": 20670.25,
      "stop_price": 20657.0,
      "target_price": 20686.75,
      "risk_pts": 13.25,
      "n_value": 1.25,
      "contracts": 2,
      "entry_time": "2024-07-09 14:50:08.946371209-04:00",
      "exit_time": "2024-07-09 14:55:40.685584287-04:00",
      "exit_price": 20657.0,
      "exit_reason": "SL",
      "pnl_pts": -13.25,
      "pnl_dollars": -539.0,
      "is_win": false,
      "group_id": "cb38717f2662",
      "fvg_id": "50a93739daf2"
    }
  ]
}