{
  "meta": {
    "source": "replay",
    "replay_date": "2024-08-23",
    "balance": 300805.0,
    "risk_pct": 0.01,
    "replay_mode": true
  },
  "summary": {
    "total_trades": 6,
    "wins": 2,
    "losses": 3,
    "eod_exits": 1,
    "net_pnl": 2055.5,
    "start_balance": 300805.0,
    "end_balance": 302860.5,
    "kill_switch_hit": false
  },
  "trades": [
    {
      "trade_id": 1,
      "date": "2024-08-23",
      "fvg_type": "",
      "time_period": "",
      "risk_range": "",
      "setup": "mit_extreme",
      "side": "BUY",
      "entry_price": 19760.5,
      "stop_price": 19748.75,
      "target_price": 19790.0,
      "risk_pts": 11.75,
      "n_value": 2.5,
      "contracts": 6,
      "entry_time": "2024-08-23 11:27:10.721965961-04:00",
      "exit_time": "2024-08-23 11:27:23.169238789-04:00",
      "exit_price": 19748.75,
      "exit_reason": "SL",
      "pnl_pts": -11.75,
      "pnl_dollars": -1437.0,
      "is_win": false,
      "group_id": "1e4f08ad96b4",
      "fvg_id": "baa6a4f39223"
    },
    {
      "trade_id": 2,
      "date": "2024-08-23",
      "fvg_type": "",
      "time_period": "",
      "risk_range": "",
      "setup": "mid_extreme",
      "side": "SELL",
      "entry_price": 19759.0,
      "stop_price": 19818.25,
      "target_price": 19655.25,
      "risk_pts": 59.25,
      "n_value": 1.75,
      "contracts": 7,
      "entry_time": "2024-08-23 13:44:25.379916831-04:00",
      "exit_time": "2024-08-23 15:59:59.998647231-04:00",
      "exit_price": 19789.0,
      "exit_reason": "EOD",
      "pnl_pts": -30.0,
      "pnl_dollars": -4231.5,
      "is_win": false,
      "group_id": "00c57556e830",
      "fvg_id": "09b03ff6fbfc"
    },
    {
      "trade_id": 3,
      "date": "2024-08-23",
      "fvg_type": "",
      "time_period": "",
      "risk_range": "",
      "setup": "mit_extreme",
      "side": "SELL",
      "entry_price": 19696.75,
      "stop_price": 19725.25,
      "target_price": 19639.75,
      "risk_pts": 28.5,
      "n_value": 2.0,
      "contracts": 7,
      "entry_time": "2024-08-23 12:36:26.646075325-04:00",
      "exit_time": "2024-08-23 12:42:37.606386725-04:00",
      "exit_price": 19639.75,
      "exit_reason": "TP",
      "pnl_pts": 57.0,
      "pnl_dollars": 7948.5,
      "is_win": true,
      "group_id": "c1858f9478df",
      "fvg_id": "0180b1c8fb0a"
    },
    {
      "trade_id": 4,
      "date": "2024-08-23",
      "fvg_type": "",
      "time_period": "",
      "risk_range": "",
      "setup": "mit_extreme",
      "side": "BUY",
      "entry_price": 19670.75,
      "stop_price": 19656.25,
      "target_price": 19699.75,
      "risk_pts": 14.5,
      "n_value": 2.0,
      "contracts": 5,
      "entry_time": "2024-08-23 12:41:00.976758003-04:00",
      "exit_time": "2024-08-23 12:42:03.217323697-04:00",
      "exit_price": 19656.25,
      "exit_reason": "SL",
      "pnl_pts": -14.5,
      "pnl_dollars": -1472.5,
      "is_win": false,
      "group_id": "8e7180133467",
      "fvg_id": "f65ebf49c6fe"
    },
    {
      "trade_id": 5,
      "date": "2024-08-23",
      "fvg_type": "",
      "time_period": "",
      "risk_range": "",
      "setup": "mit_extreme",
      "side": "BUY",
      "entry_price": 19724.0,
      "stop_price": 19706.75,
      "target_price": 19741.25,
      "risk_pts": 17.25,
      "n_value": 1.0,
      "contracts": 8,
      "entry_time": "2024-08-23 13:35:08.785271001-04:00",
      "exit_time": "2024-08-23 13:39:25.052964237-04:00",
      "exit_price": 19741.25,
      "exit_reason": "TP",
      "pnl_pts": 17.25,
      "pnl_dollars": 2724.0,
      "is_win": true,
      "group_id": "b49c0f628662",
      "fvg_id": "854b9cc68648"
    },
    {
      "trade_id": 6,
      "date": "2024-08-23",
      "fvg_type": "",
      "time_period": "",
      "risk_range": "",
      "setup": "mit_extreme",
      "side": "BUY",
      "entry_price": 19754.5,
      "stop_price": 19745.5,
      "target_price": 19768.0,
      "risk_pts": 9.0,
      "n_value": 1.5,
      "contracts": 8,
      "entry_time": "2024-08-23 14:51:34.924804969-04:00",
      "exit_time": "2024-08-23 14:57:16.419155403-04:00",
      "exit_price": 19745.5,
      "exit_reason": "SL",
      "pnl_pts": -9.0,
      "pnl_dollars": -1476.0,
      "is_win": false,
      "group_id": "40b487310da5",
      "fvg_id": "223e8596edb6"
    }
  ]
}