{
  "meta": {
    "source": "replay",
    "replay_date": "2024-01-22",
    "balance": 104785.0,
    "risk_pct": 0.01,
    "replay_mode": true
  },
  "summary": {
    "total_trades": 1,
    "wins": 1,
    "losses": 0,
    "eod_exits": 0,
    "net_pnl": 1096.5,
    "start_balance": 104785.0,
    "end_balance": 105881.5,
    "kill_switch_hit": false
  },
  "trades": [
    {
      "trade_id": 1,
      "date": "2024-01-22",
      "fvg_type": "",
      "time_period": "",
      "risk_range": "",
      "setup": "mit_extreme",
      "side": "SELL",
      "entry_price": 17473.0,
      "stop_price": 17481.25,
      "target_price": 17454.5,
      "risk_pts": 8.25,
      "n_value": 2.25,
      "contracts": 3,
      "entry_time": "2024-01-22 14:32:14.785839677-05:00",
      "exit_time": "2024-01-22 14:34:14.559604421-05:00",
      "exit_price": 17454.5,
      "exit_reason": "TP",
      "pnl_pts": 18.5,
      "pnl_dollars": 1096.5,
      "is_win": true,
      "group_id": "60251abaec12",
      "fvg_id": "4353e70efe65"
    }
  ]
}